[{"ImageName":"Sonic US.png","ImageDescription":"Sonic US","ImageColumn":1},{"ImageName":"Canelita.gif","ImageDescription":"Canelita","ImageColumn":2},{"ImageName":"Generator Room Cortex.gif","ImageDescription":"Generator Room Cortex","ImageColumn":3},{"ImageName":"Meatsona.png","ImageDescription":"Meatsona","ImageColumn":1},{"ImageName":"Relationship Goals.png","ImageDescription":"Relationship Goals","ImageColumn":2},{"ImageName":"Dragon Ball Super.png","ImageDescription":"Tournament of Power Arena","ImageColumn":3}]